dnpak/__init__.py
dnpak/etfile.py
dnpak/etfilesystem.py
dnpak/utils.py
dnpak.py-2.0.0.dist-info/LICENSE
dnpak.py-2.0.0.dist-info/METADATA
dnpak.py-2.0.0.dist-info/WHEEL
dnpak.py-2.0.0.dist-info/top_level.txt
dnpak.py-2.0.0.dist-info/RECORD
