Metadata-Version: 2.1
Name: dnpak.py
Version: 2.0.0
Summary: A python package to manipulate DragonNest pak file
Home-page: https://github.com/Veirt/dnpak.py
Author: Muhammad Dony Mulya
Author-email: vveirt@gmail.com
License: WTFPL
Keywords: dragonnest
Platform: UNKNOWN
Classifier: Programming Language :: Python :: 3.6
Classifier: Programming Language :: Python :: 3.7
Classifier: Programming Language :: Python :: 3.8
Classifier: Programming Language :: Python :: 3.9
Classifier: Intended Audience :: Developers
Classifier: License :: Other/Proprietary License
License-File: LICENSE
